LICENSE
MANIFEST.in
README.md
pyproject.toml
setup.py
layerd/__init__.py
layerd/__main__.py
layerd/package.py
layerd/utils.py
layerd.egg-info/PKG-INFO
layerd.egg-info/SOURCES.txt
layerd.egg-info/dependency_links.txt
layerd.egg-info/entry_points.txt
layerd.egg-info/requires.txt
layerd.egg-info/top_level.txt