Metadata-Version: 2.1
Name: layerd
Version: 2023.4.24.12.34
Summary: Download AWS Lambda Layers.
Home-page: https://github.com/ronnathaniel/layerd
Author: ronnathaniel
Author-email: rnathaniel7@gmail.com
Project-URL: Bug Tracker, https://github.com/ronnathaniel/layerd/issues
Keywords: python,python3,layerd,daemon,download,layer,extension,aws,lambda,function,remote
Classifier: Intended Audience :: Developers
Classifier: Operating System :: OS Independent
Classifier: Programming Language :: Python
Classifier: Programming Language :: Python :: 2
Classifier: Programming Language :: Python :: 2.7
Classifier: Programming Language :: Python :: 3
Classifier: Programming Language :: Python :: 3.6
Classifier: Programming Language :: Python :: 3.7
Classifier: Programming Language :: Python :: 3.8
Classifier: Topic :: Software Development :: Libraries
Classifier: Topic :: Software Development :: Libraries :: Python Modules
Requires-Python: >=3.6
License-File: LICENSE
